implementation/src/Qcount.vhdl
library IEEE;
  use IEEE.std_logic_1164.all; 
  use IEEE.numeric_std.all;
  
entity Qcount is port( 
  clk, reset : in  std_logic; 
  count      : out std_logic_vector(2 downto 0));
end entity Qcount;

architecture RTL of Qcount is
  signal r_count, next_count : unsigned(count'range);  
begin
  process(clk) is begin 
    if rising_edge(clk) then 
      r_count <= (others => '0') when reset else next_count;
    end if;
  end process;
  count <= std_logic_vector(r_count); 
  next_count <= (others => '0') when r_count = 4 else r_count + 1;
end architecture RTL;

GHDL/usage-examples/src/tb_FIAT_min.vhdl
library IEEE;
  use IEEE.std_logic_1164.all; 
  use IEEE.numeric_std.all;

entity tb_fiat is
end entity tb_fiat;

architecture behavioral of tb_fiat is  
  component Qcount is port( 
    clk, reset       : in  std_logic; 
    count            : out std_logic_vector(2 downto 0));
  end component Qcount;
  
  constant N: integer := 3;
  signal clk, reset : std_logic := '1';
  signal tQcount      : integer := 0;
  signal count       : std_logic_vector(N-1 downto 0);
  
begin 

  DUT: Qcount 
    port map(
      reset => reset,
      clk => clk,
      count => count      
    );

  BEHAVIORAL_MODEL:
    process is 
    begin
      wait until rising_edge(clk);    
      tQcount <= 
        0 when reset else 
        0 when tQcount = 4 else
        tQcount+1;
    end process;
  
  CLOCK: 
    clk <= not clk after 5 ns;
    
  CHECKS:
    process is 
      variable DUTcount: integer; 
    begin 
      wait until clk'event;
      DUTcount := to_integer(unsigned(count));      
      --model equivalence
      assert DUTcount = tQcount report("count (" & integer'image(DUTcount) & 
        ") != behavioral model: ("& integer'image(tQcount) & ")");
      --maximum value 
      assert DUTcount < 5 report ("count (" & integer'image(DUTcount) & ") > 4, ** Maximum value exceeded");
    end process;  
    
  
  FAULT_INJECTION:
    process is
      procedure reset_and_wait(count_value: integer) is 
      begin 
        wait until unsigned(count) = 0;
        reset <= '1';
        wait until rising_edge(clk);
        reset <= '0';
        wait until unsigned(count) = count_value;
        wait until falling_edge(clk);
      end procedure;
      
      procedure BLACKBOX_INJECT_TOO_HIGH_VALUE is 
        constant force_value : integer := 5;
      begin        
        count <= force std_logic_vector(to_unsigned(force_value, N));  
        wait until rising_edge(clk);
        count <= release;
      end procedure;
 
      procedure WHITEBOX_INJECT_TOO_HIGH_VALUE is
        constant force_value : integer := 6;
        alias wb_count is <<signal DUT.r_count : unsigned(N-1 downto 0)>>;
      begin        
        wb_count <= force to_unsigned(force_value, N);
        wait until rising_edge(clk);
        wb_count <= release;
      end procedure;
  
    begin
      reset_and_wait(2);
      BLACKBOX_INJECT_TOO_HIGH_VALUE;
      reset_and_wait(3);
      WHITEBOX_INJECT_TOO_HIGH_VALUE;
      reset_and_wait(4);
      std.env.stop;
    end process;
  
end architecture behavioral;

Questa/usage-examples/vhdl_min.vcd
$date
	Thu Oct 19 12:21:09 2023
$end
$version
	QuestaSim Version 2020.4
$end
$timescale
	1ns
$end
$scope module tb_fiat $end
$var wire 1 ! clk $end
$var wire 1 " reset $end
$var integer 32 # tQcount $end
$var wire 1 $ count [2] $end
$var wire 1 % count [1] $end
$var wire 1 & count [0] $end
$upscope $end
$enddefinitions $end
#0
1!
1"
b0 #
x$
x%
x&
#5
0!
#10
1!
0$
0%
0&
#15
0!
#20
1!
0"
#25
0!
#30
1!
b1 #
1&
#35
0!
#40
1!
b10 #
1%
0&
#45
0!
1$
0%
1&
#50
1!
b11 #
0$
1%
1&
#55
0!
#60
1!
b100 #
1$
0%
0&
#65
0!
#70
1!
b0 #
0$
1"
#75
0!
#80
1!
0"
#85
0!
#90
1!
b1 #
1&
#95
0!
#100
1!
b10 #
1%
0&
#105
0!
#110
1!
b11 #
1&
#115
0!
1$
0&
#120
1!
b100 #
1&
#125
0!
#130
1!
b0 #
0$
0%
0&
1"
#135
0!
#140
1!
0"
#145
0!
#150
1!
b1 #
1&
#155
0!
#160
1!
b10 #
1%
0&
#165
0!
#170
1!
b11 #
1&
#175
0!
#180
1!
b100 #
1$
0%
0&
